django_fast/__init__.py
django_fast/cli.py
django_fast/project_scaffolder.py
django_fast/core/__init__.py
django_fast/core/app.py
django_fast/core/django_orm.py
django_fast/core/response.py
django_fast/core/router.py
django_fast/templates/project_template/__init__.py
django_fast/templates/project_template/main.py
django_fast/templates/project_template/manage.py
django_fast/templates/project_template/models.py
django_fast/templates/project_template/settings.py
django_fast/templates/project_template/urls.py
django_fast-0.2.0.dist-info/METADATA
django_fast-0.2.0.dist-info/WHEEL
django_fast-0.2.0.dist-info/top_level.txt
django_fast-0.2.0.dist-info/RECORD
