Metadata-Version: 2.4
Name: django-fast
Version: 0.2.0
Summary: A fast Django-like microframework
Home-page: https://github.com/Madhav89755/DjangoFast
Author: Your Name
Author-email: madhav.sharma2002.12@gmail.com
Classifier: Programming Language :: Python :: 3
Classifier: License :: OSI Approved :: MIT License
Classifier: Operating System :: OS Independent
Requires-Python: >=3.8
Requires-Dist: django<5.0,>=4.2
Requires-Dist: uvicorn<1.0,>=0.22
Dynamic: author
Dynamic: author-email
Dynamic: classifier
Dynamic: home-page
Dynamic: requires-dist
Dynamic: requires-python
Dynamic: summary
